abs_langchain_core/__init__.py
abs_langchain_core/callbacks/__init__.py
abs_langchain_core/callbacks/token_tracker.py
abs_langchain_core/core/__init__.py
abs_langchain_core/core/config.py
abs_langchain_core/core/llm_provider.py
abs_langchain_core/core/logger.py
abs_langchain_core/interfaces/embedding_provider.py
abs_langchain_core/mixins/__init__.py
abs_langchain_core/mixins/embedding_hook.py
abs_langchain_core/models/__init__.py
abs_langchain_core/models/usage.py
abs_langchain_core/providers/openai_provider.py
abs_langchain_core/schemas/__init__.py
abs_langchain_core/schemas/cosmo_vector_config_schema.py
abs_langchain_core/schemas/embedding_config_schema.py
abs_langchain_core/schemas/embedding_metadata_schema.py
abs_langchain_core/schemas/embedding_request_schema.py
abs_langchain_core/schemas/embedding_response_schema.py
abs_langchain_core/services/__init__.py
abs_langchain_core/services/agent.py
abs_langchain_core/services/base.py
abs_langchain_core/services/chat.py
abs_langchain_core/services/embedding_service.py
abs_langchain_core/services/pricing.py
abs_langchain_core/services/rag.py
abs_langchain_core-0.1.4.dist-info/METADATA
abs_langchain_core-0.1.4.dist-info/WHEEL
abs_langchain_core-0.1.4.dist-info/RECORD
