Metadata-Version: 2.3
Name: abs-langchain-core
Version: 0.1.4
Summary: LangChain utilities with token tracking, RAG, and agent support
License: MIT
Author: AutoBridgeSystems
Author-email: info@autobridgesystems.com
Requires-Python: >=3.13,<4.0
Classifier: License :: OSI Approved :: MIT License
Classifier: Programming Language :: Python :: 3
Classifier: Programming Language :: Python :: 3.13
Requires-Dist: abs-exception-core (>=0.1.2,<0.2.0)
Requires-Dist: azure-cosmos (>=4.9.0,<5.0.0)
Requires-Dist: langchain (>=0.3.25)
Requires-Dist: langchain-community (>=0.0.10)
Requires-Dist: langchain-core (>=0.3.60)
Requires-Dist: langchain-openai (>=0.0.2)
Requires-Dist: openai (>=1.10.0)
Requires-Dist: pydantic (>=2.0.0,<3.0.0)
Requires-Dist: sqlalchemy (>=2.0.0,<3.0.0)
